{
  "_find_impl": {
    "raises": [
      "RuntimeError"
    ]
  },
  "cached_property.__get__": {
    "raises": [
      "TypeError"
    ]
  },
  "cached_property.__set_name__": {
    "raises": [
      "TypeError"
    ]
  },
  "lru_cache": {
    "raises": [
      "TypeError"
    ]
  },
  "partial.__call__": {
    "raises": [
      "TypeError"
    ]
  },
  "partial.__new__": {
    "raises": [
      "TypeError"
    ]
  },
  "partial.__setstate__": {
    "raises": [
      "TypeError"
    ]
  },
  "partialmethod.__init__": {
    "raises": [
      "TypeError"
    ]
  },
  "reduce": {
    "raises": [
      "TypeError"
    ]
  },
  "singledispatch": {
    "has": [
      "import"
    ]
  },
  "singledispatchmethod.__init__": {
    "has": [
      "import"
    ],
    "raises": [
      "TypeError"
    ]
  },
  "singledispatchmethod.register": {
    "has": [
      "global",
      "import"
    ],
    "raises": [
      "TypeError"
    ]
  },
  "total_ordering": {
    "raises": [
      "ValueError"
    ]
  }
}